yahoo_prices/__init__.py
yahoo_prices/prices_table.py
yahoo_prices/update_db.py
yahoo_prices/utils.py
yahoo_prices-0.3.7.dist-info/WHEEL
yahoo_prices-0.3.7.dist-info/METADATA
yahoo_prices-0.3.7.dist-info/RECORD
