Metadata-Version: 2.1
Name: yahoo-prices
Version: 0.3.7
Summary: Light weight python package for downloading yahoo-finance prices
Author: aghazaly
Author-email: ahmed.ghazaly.1@gmail.com
Requires-Python: >=3.7.4,<4.0.0
Classifier: Programming Language :: Python :: 3
Classifier: Programming Language :: Python :: 3.8
Classifier: Programming Language :: Python :: 3.9
Requires-Dist: SQLAlchemy (>=1.3.23,<2.0.0)
Requires-Dist: pandas (>=1.2.3,<2.0.0)
Requires-Dist: pandas-datareader (>=0.9.0,<0.10.0)
Requires-Dist: tqdm (>=4.59.0,<5.0.0)
